fatecast/__init__.py
fatecast/__main__.py
fatecast/cli.py
fatecast/logic.py
fatecast/styles.tcss
fatecast/ui.py
tests/test_logic.py
fatecast-0.1.0.dist-info/LICENSE
fatecast-0.1.0.dist-info/METADATA
fatecast-0.1.0.dist-info/WHEEL
fatecast-0.1.0.dist-info/entry_points.txt
fatecast-0.1.0.dist-info/top_level.txt
fatecast-0.1.0.dist-info/RECORD
