Metadata-Version: 2.1
Name: fatecast
Version: 0.1.0
Summary: A Textual-powered Chaoshan cup divination mini game.
Author: dongfan
License: MIT License
Project-URL: Homepage, https://github.com/dongfan/fatecast
Project-URL: Repository, https://github.com/dongfan/fatecast
Project-URL: Issues, https://github.com/dongfan/fatecast/issues
Keywords: textual,tui,cup-divination,chaoshan,terminal
Classifier: Development Status :: 4 - Beta
Classifier: Environment :: Console
Classifier: Environment :: Console :: Curses
Classifier: License :: OSI Approved :: MIT License
Classifier: Programming Language :: Python :: 3
Classifier: Programming Language :: Python :: 3.10
Classifier: Programming Language :: Python :: 3.11
Classifier: Programming Language :: Python :: 3.12
Classifier: Intended Audience :: End Users/Desktop
Classifier: Topic :: Games/Entertainment
Classifier: Topic :: Religion
Classifier: Topic :: Terminals
Requires-Python: >=3.10
License-File: LICENSE
Requires-Dist: textual>=0.55
